<?xml version="1.0" encoding="utf-8" ?>
<sig:tasks xmlns:sig="urn:simpleGrader">
    <sig:task id="1000" exercise="EA1" passingMark="0.9" level="A" title="Math-Tester">
        <description>Simple math functions</description>
        <files>
            <file>MyMath.java</file>
            <file>MyMathTester.java</file>
        </files>
        <actions>
            <action id="1" active="True" type="java-compile">compile java file</action>
        </actions>
        <tests>
            <test id="1" active="True">
                <test-type>TestDriver</test-type>
                <test-name>Output-Comparsion</test-name>
                <test-description>Compares output with test driver</test-description>
                <test-driver>MyMathTester</test-driver>
                <test-score>4</test-score>
            </test>
            <test id="2" active="True">
                <test-type>JUnit</test-type>
                <test-name>JUnit 1</test-name>
                <test-class>AppTest</test-class>
                <test-description>Add numbers</test-description>
                <test-method>testAddNumbers1</test-method>
                <test-score>1</test-score>
            </test>
            <test id="3" active="True">
                <test-type>JUnit</test-type>
                <test-name>JUnit 2</test-name>
                <test-class>AppTest</test-class>
                <test-description>Subtract Numbers</test-description>
                <test-method>testSubtractNumbers1</test-method>
                <test-score>1</test-score>
            </test>
            <test id="4" active="False">
                <test-type>JUnit</test-type>
                <test-name>JUnit 3</test-name>
                <test-class>AppTest</test-class>
                <test-description>Subtract negative Numbers</test-description>
                <test-method>testSubtractNumbers2</test-method>
                <test-score>1</test-score>
            </test>
        </tests>
    </sig:task>
    <sig:task id="1001" exercise="EA2" level="A" passingMark="0.8" title="SimpleCar-Tester">
        <description>Tests for the simple car class</description>
        <files>
            <file>SimpleCar.java</file>
            <file>MovingCarTester.java</file>
        </files>
        <actions>
            <action id="1" active="True" type="java-compile">compile java file</action>
        </actions>
        <tests>
            <test id="1" active="True">
                <test-type>TestDriver</test-type>
                <test-name>Output-Comparsion</test-name>
                <test-description>Compares output with test driver</test-description>
                <test-driver>MovingCarTester</test-driver>
                <test-score>4</test-score>
            </test>
        </tests>
    </sig:task>
    <sig:task id="1003" exercise="EA3" level="A" passingMark="0.8" title="Resistor Codes">
        <description>Tests for Resistor ring coloring</description>
        <files>
            <file>ElectronicColorCode.java</file>
            <file>Resistor.java</file>
            <file>ResistorTester.java</file>
            <file>ToleranceStation.java</file>
        </files>
        <actions>
            <action id="1" active="True" type="java-compile">compile java file</action>
        </actions>
        <tests>
            <test id="1" active="True">
                <test-type>TestDriver</test-type>
                <test-name>Output-Comparsion</test-name>
                <test-description>Compares output with test driver</test-description>
                <test-driver>ResistorTester</test-driver>
                <test-score>8</test-score>
            </test>
        </tests>
    </sig:task>
</sig:tasks>
